WebSite2PDF/__init__.py
WebSite2PDF/client.py
WebSite2PDF/driver/__init__.py
WebSite2PDF/driver/driver.py
WebSite2PDF/errors/__init__.py
WebSite2PDF/errors/rpc_error.py
WebSite2PDF-0.1.1.dist-info/LICENSE
WebSite2PDF-0.1.1.dist-info/METADATA
WebSite2PDF-0.1.1.dist-info/WHEEL
WebSite2PDF-0.1.1.dist-info/top_level.txt
WebSite2PDF-0.1.1.dist-info/RECORD
