Metadata-Version: 2.1
Name: WebSite2PDF
Version: 0.1.1
Summary: Simple and Fast Python framework to convert HTML files or Web Site to PDF
Home-page: https://github.com/uNickz/WebSite2PDF
Download-URL: https://github.com/uNickz/WebSite2PDF/releases/latest
Author: uNickz
Author-email: unickz.dev@gmail.com
License: LGPLv3
Project-URL: Tracker, https://github.com/uNickz/WebSite2PDF/issues
Project-URL: Source, https://github.com/uNickz/WebSite2PDF
Project-URL: Documentation, https://github.com/uNickz/WebSite2PDF/blob/main/README.md
Keywords: python file html site website pdf converter convert
Classifier: Development Status :: 5 - Production/Stable
Classifier: Intended Audience :: Developers
Classifier: License :: OSI Approved :: GNU Lesser General Public License v3 (LGPLv3)
Classifier: Operating System :: OS Independent
Classifier: Programming Language :: Python
Classifier: Programming Language :: Python :: 3
Requires-Python: >=3.7
License-File: LICENSE
Requires-Dist: webdriver-manager
Requires-Dist: selenium
Requires-Dist: requests
